README.rst
setup.cfg
setup.py
datacoco_db/__init__.py
datacoco_db/__version__.py
datacoco_db/dynamo_tools.py
datacoco_db/mongo_tools.py
datacoco_db/mssql_tools.py
datacoco_db/mysql_tools.py
datacoco_db/pg_tools.py
datacoco_db/rdb_tools.py
datacoco_db/sqlite_tools.py
datacoco_db.egg-info/PKG-INFO
datacoco_db.egg-info/SOURCES.txt
datacoco_db.egg-info/dependency_links.txt
datacoco_db.egg-info/requires.txt
datacoco_db.egg-info/top_level.txt
datacoco_db/helper/__init__.py
datacoco_db/helper/deprecate.py
sqlalchemy_pytds/__init__.py
sqlalchemy_pytds/connector.py
sqlalchemy_pytds/dialect.py
sqlalchemy_pytds/requirements.py