Metadata-Version: 1.0
Name: datacoco-db
Version: 0.1.10
Summary: Data common code for database interactions by Equinox
Home-page: https://github.com/equinoxfitness/datacoco-db
Author: Equinox Fitness
Author-email: UNKNOWN
License: MIT
Platform: UNKNOWN
